{
  "properties": {
    "property_details": {
      "properties": {
        "bathrooms": {
          "description": "The number of bathrooms in the property",
          "type": "integer"
        },
        "bedrooms": {
          "description": "The number of bedrooms in the property",
          "type": "integer"
        },
        "location": {
          "description": "The location of the property",
          "type": "string"
        }
      },
      "required": [
        "location",
        "bedrooms",
        "bathrooms"
      ],
      "type": "object"
    }
  },
  "required": [
    "property_details"
  ],
  "type": "object"
}